LICENSE
MANIFEST.in
README.md
setup.cfg
setup.py
firstlanguage_python/__init__.py
firstlanguage_python/api_helper.py
firstlanguage_python/configuration.py
firstlanguage_python/decorators.py
firstlanguage_python/firstlanguage_client.py
firstlanguage_python.egg-info/PKG-INFO
firstlanguage_python.egg-info/SOURCES.txt
firstlanguage_python.egg-info/dependency_links.txt
firstlanguage_python.egg-info/requires.txt
firstlanguage_python.egg-info/top_level.txt
firstlanguage_python/controllers/__init__.py
firstlanguage_python/controllers/advanced_api_controller.py
firstlanguage_python/controllers/base_controller.py
firstlanguage_python/controllers/basic_api_controller.py
firstlanguage_python/controllers/enterprise_only_controller.py
firstlanguage_python/exceptions/__init__.py
firstlanguage_python/exceptions/api_classify_426_error_exception.py
firstlanguage_python/exceptions/api_exception.py
firstlanguage_python/exceptions/api_lemmatize_426_error_exception.py
firstlanguage_python/exceptions/api_morph_426_error_exception.py
firstlanguage_python/exceptions/api_postag_426_error_exception.py
firstlanguage_python/exceptions/api_stemmer_426_error_exception.py
firstlanguage_python/exceptions/errors_exception.py
firstlanguage_python/exceptions/m_426_error_exception.py
firstlanguage_python/http/__init__.py
firstlanguage_python/http/http_call_back.py
firstlanguage_python/http/http_client.py
firstlanguage_python/http/http_method_enum.py
firstlanguage_python/http/http_request.py
firstlanguage_python/http/http_response.py
firstlanguage_python/http/requests_client.py
firstlanguage_python/http/auth/__init__.py
firstlanguage_python/http/auth/custom_header_authentication.py
firstlanguage_python/models/__init__.py
firstlanguage_python/models/api_imagecaption_request.py
firstlanguage_python/models/api_imagecaption_response.py
firstlanguage_python/models/api_ner_request.py
firstlanguage_python/models/api_ner_request_1.py
firstlanguage_python/models/api_ner_response.py
firstlanguage_python/models/api_qa_request.py
firstlanguage_python/models/api_qa_request_1.py
firstlanguage_python/models/api_qa_response.py
firstlanguage_python/models/api_question_request.py
firstlanguage_python/models/api_question_response.py
