Metadata-Version: 2.1
Name: firstlanguage-python
Version: 2.1
Summary: Python client library for FirstLanguage API
Home-page: https://www.firstlanguage.in/contactus
Author: FirstLanguage
Author-email: info@firstlanguage.in
License: UNKNOWN
Download-URL: https://github.com/FirstLanguage/firstlanguage_python/archive/refs/tags/v2.1.tar.gz
Keywords: FirstLanguage API,NLP,SDK,Python,Natural Language Processing
Platform: UNKNOWN
